CONTRIBUTING.md
DEVELOP.md
MANIFEST.in
README.rst
constraints.txt
setup.cfg
setup.py
docs/HISTORY.txt
docs/INSTALL.txt
docs/LICENSE.GPL
docs/LICENSE.txt
eea/__init__.py
eea.facetednavigation.egg-info/PKG-INFO
eea.facetednavigation.egg-info/SOURCES.txt
eea.facetednavigation.egg-info/dependency_links.txt
eea.facetednavigation.egg-info/entry_points.txt
eea.facetednavigation.egg-info/namespace_packages.txt
eea.facetednavigation.egg-info/not-zip-safe
eea.facetednavigation.egg-info/requires.txt
eea.facetednavigation.egg-info/top_level.txt
eea/facetednavigation/README.txt
eea/facetednavigation/__init__.py
eea/facetednavigation/config.py
eea/facetednavigation/configure.zcml
eea/facetednavigation/events.py
eea/facetednavigation/interfaces.py
eea/facetednavigation/meta.zcml
eea/facetednavigation/overrides.zcml
eea/facetednavigation/permissions.zcml
eea/facetednavigation/plonex.py
eea/facetednavigation/profiles.zcml
eea/facetednavigation/setuphandlers.py
eea/facetednavigation/utils.py
eea/facetednavigation/version.txt
eea/facetednavigation/browser/__init__.py
eea/facetednavigation/browser/configure.zcml
eea/facetednavigation/browser/interfaces.py
eea/facetednavigation/browser/app/__init__.py
eea/facetednavigation/browser/app/catalog.py
eea/facetednavigation/browser/app/configure.py
eea/facetednavigation/browser/app/counter.py
eea/facetednavigation/browser/app/error.py
eea/facetednavigation/browser/app/exportimport.py
eea/facetednavigation/browser/app/query.py
eea/facetednavigation/browser/app/schema.py
eea/facetednavigation/browser/app/view.py
eea/facetednavigation/browser/javascript/edit.js
eea/facetednavigation/browser/javascript/expand.js
eea/facetednavigation/browser/javascript/independent.js
eea/facetednavigation/browser/javascript/view.js
eea/facetednavigation/browser/static/30px.png
eea/facetednavigation/browser/static/32px.png
eea/facetednavigation/browser/static/README.md
eea/facetednavigation/browser/static/ajax-loader-small.gif
eea/facetednavigation/browser/static/ajax-loader.gif
eea/facetednavigation/browser/static/faceted-edit.css
eea/facetednavigation/browser/static/faceted-edit.css.map
eea/facetednavigation/browser/static/faceted-edit.min.css
eea/facetednavigation/browser/static/faceted-edit.min.css.map
eea/facetednavigation/browser/static/faceted-edit.min.js
eea/facetednavigation/browser/static/faceted-jquery.css
